[
    {
        "puzzlenumber" : "1",
        "puzzlepiece" : "8",
        "puzzlepieceid" : "1"
    },
    {
        "puzzlenumber" : "1",
        "puzzlepiece" : "5",
        "puzzlepieceid" : "2"
    },
    {
        "puzzlenumber" : "1",
        "puzzlepiece" : "25",
        "puzzlepieceid" : "3"
    },
    {
        "puzzlenumber" : "1",
        "puzzlepiece" : "20",
        "puzzlepieceid" : "4"
    },
    {
        "puzzlenumber" : "1",
        "puzzlepiece" : "8",
        "puzzlepieceid" : "5"
    },
    {
        "puzzlenumber" : "1",
        "puzzlepiece" : "9",
        "puzzlepieceid" : "6"
    },
    {
        "puzzlenumber" : "1",
        "puzzlepiece" : "19",
        "puzzlepieceid" : "7"
    },
    {
        "puzzlenumber" : "1",
        "puzzlepiece" : "9",
        "puzzlepieceid" : "8"
    },
    {
        "puzzlenumber" : "1",
        "puzzlepiece" : "19",
        "puzzlepieceid" : "9"
    },
    {
        "puzzlenumber" : "1",
        "puzzlepiece" : "7",
        "puzzlepieceid" : "10"
    },
    {
        "puzzlenumber" : "1",
        "puzzlepiece" : "18",
        "puzzlepieceid" : "11"
    },
    {
        "puzzlenumber" : "1",
        "puzzlepiece" : "5",
        "puzzlepieceid" : "12"
    },
    {
        "puzzlenumber" : "1",
        "puzzlepiece" : "7",
        "puzzlepieceid" : "13"
    },
    {
        "puzzlenumber" : "1",
        "puzzlepiece" : "6",
        "puzzlepieceid" : "14"
    },
    {
        "puzzlenumber" : "1",
        "puzzlepiece" : "18",
        "puzzlepieceid" : "15"
    },
    {
        "puzzlenumber" : "1",
        "puzzlepiece" : "15",
        "puzzlepieceid" : "16"
    },
    {
        "puzzlenumber" : "1",
        "puzzlepiece" : "13",
        "puzzlepieceid" : "17"
    },
    {
        "puzzlenumber" : "1",
        "puzzlepiece" : "1",
        "puzzlepieceid" : "18"
    },
    {
        "puzzlenumber" : "1",
        "puzzlepiece" : "16",
        "puzzlepieceid" : "19"
    },
    {
        "puzzlenumber" : "1",
        "puzzlepiece" : "16",
        "puzzlepieceid" : "20"
    },
    {
        "puzzlenumber" : "1",
        "puzzlepiece" : "12",
        "puzzlepieceid" : "21"
    },
    {
        "puzzlenumber" : "1",
        "puzzlepiece" : "5",
        "puzzlepieceid" : "22"
    },
    {
        "puzzlenumber" : "1",
        "puzzlepiece" : "5",
        "puzzlepieceid" : "23"
    },
    {
        "puzzlenumber" : "1",
        "puzzlepiece" : "24",
        "puzzlepieceid" : "24"
    },
    {
        "puzzlenumber" : "1",
        "puzzlepiece" : "16",
        "puzzlepieceid" : "25"
    },
    {
        "puzzlenumber" : "1",
        "puzzlepiece" : "12",
        "puzzlepieceid" : "26"
    },
    {
        "puzzlenumber" : "1",
        "puzzlepiece" : "1",
        "puzzlepieceid" : "27"
    },
    {
        "puzzlenumber" : "1",
        "puzzlepiece" : "9",
        "puzzlepieceid" : "28"
    },
    {
        "puzzlenumber" : "1",
        "puzzlepiece" : "14",
        "puzzlepieceid" : "29"
    },
    {
        "puzzlenumber" : "1",
        "puzzlepiece" : "5",
        "puzzlepieceid" : "30"
    },
    {
        "puzzlenumber" : "1",
        "puzzlepiece" : "4",
        "puzzlepieceid" : "31"
    },
    {
        "puzzlenumber" : "1",
        "puzzlepiece" : "14",
        "puzzlepieceid" : "32"
    },
    {
        "puzzlenumber" : "1",
        "puzzlepiece" : "15",
        "puzzlepieceid" : "33"
    },
    {
        "puzzlenumber" : "1",
        "puzzlepiece" : "23",
        "puzzlepieceid" : "34"
    },
    {
        "puzzlenumber" : "1",
        "puzzlepiece" : "13",
        "puzzlepieceid" : "35"
    },
    {
        "puzzlenumber" : "1",
        "puzzlepiece" : "25",
        "puzzlepieceid" : "36"
    },
    {
        "puzzlenumber" : "1",
        "puzzlepiece" : "12",
        "puzzlepieceid" : "37"
    },
    {
        "puzzlenumber" : "1",
        "puzzlepiece" : "9",
        "puzzlepieceid" : "38"
    },
    {
        "puzzlenumber" : "1",
        "puzzlepiece" : "22",
        "puzzlepieceid" : "39"
    },
    {
        "puzzlenumber" : "1",
        "puzzlepiece" : "5",
        "puzzlepieceid" : "40"
    },
    {
        "puzzlenumber" : "1",
        "puzzlepiece" : "19",
        "puzzlepieceid" : "41"
    },
    {
        "puzzlenumber" : "1",
        "puzzlepiece" : "20",
        "puzzlepieceid" : "42"
    },
    {
        "puzzlenumber" : "1",
        "puzzlepiece" : "18",
        "puzzlepieceid" : "43"
    },
    {
        "puzzlenumber" : "1",
        "puzzlepiece" : "5",
        "puzzlepieceid" : "44"
    },
    {
        "puzzlenumber" : "1",
        "puzzlepiece" : "1",
        "puzzlepieceid" : "45"
    },
    {
        "puzzlenumber" : "1",
        "puzzlepiece" : "13",
        "puzzlepieceid" : "46"
    },
    {
        "puzzlenumber" : "1",
        "puzzlepiece" : "9",
        "puzzlepieceid" : "47"
    },
    {
        "puzzlenumber" : "1",
        "puzzlepiece" : "19",
        "puzzlepieceid" : "48"
    },
    {
        "puzzlenumber" : "1",
        "puzzlepiece" : "12",
        "puzzlepieceid" : "49"
    },
    {
        "puzzlenumber" : "1",
        "puzzlepiece" : "9",
        "puzzlepieceid" : "50"
    },
    {
        "puzzlenumber" : "1",
        "puzzlepiece" : "22",
        "puzzlepieceid" : "50"
    },
    {
        "puzzlenumber" : "1",
        "puzzlepiece" : "5",
        "puzzlepieceid" : "51"
    },
    {
        "puzzlenumber" : "2",
        "puzzlepiece" : "9",
        "puzzlepieceid" : "1"
    },
    {
        "puzzlenumber" : "2",
        "puzzlepiece" : "20",
        "puzzlepieceid" : "2"
    },
    {
        "puzzlenumber" : "2",
        "puzzlepiece" : "19",
        "puzzlepieceid" : "3"
    },
    {
        "puzzlenumber" : "2",
        "puzzlepiece" : "22",
        "puzzlepieceid" : "4"
    },
    {
        "puzzlenumber" : "2",
        "puzzlepiece" : "5",
        "puzzlepieceid" : "5"
    },
    {
        "puzzlenumber" : "2",
        "puzzlepiece" : "18",
        "puzzlepieceid" : "6"
    },
    {
        "puzzlenumber" : "2",
        "puzzlepiece" : "25",
        "puzzlepieceid" : "7"
    },
    {
        "puzzlenumber" : "2",
        "puzzlepiece" : "19",
        "puzzlepieceid" : "8"
    },
    {
        "puzzlenumber" : "2",
        "puzzlepiece" : "1",
        "puzzlepieceid" : "9"
    },
    {
        "puzzlenumber" : "2",
        "puzzlepiece" : "4",
        "puzzlepieceid" : "10"
    },
    {
        "puzzlenumber" : "2",
        "puzzlepiece" : "19",
        "puzzlepieceid" : "11"
    },
    {
        "puzzlenumber" : "2",
        "puzzlepiece" : "5",
        "puzzlepieceid" : "12"
    },
    {
        "puzzlenumber" : "2",
        "puzzlepiece" : "5",
        "puzzlepieceid" : "13"
    },
    {
        "puzzlenumber" : "2",
        "puzzlepiece" : "9",
        "puzzlepieceid" : "14"
    },
    {
        "puzzlenumber" : "2",
        "puzzlepiece" : "14",
        "puzzlepieceid" : "15"
    },
    {
        "puzzlenumber" : "2",
        "puzzlepiece" : "7",
        "puzzlepieceid" : "16"
    },
    {
        "puzzlenumber" : "2",
        "puzzlepiece" : "14",
        "puzzlepieceid" : "17"
    },
    {
        "puzzlenumber" : "2",
        "puzzlepiece" : "9",
        "puzzlepieceid" : "18"
    },
    {
        "puzzlenumber" : "2",
        "puzzlepiece" : "3",
        "puzzlepieceid" : "19"
    },
    {
        "puzzlenumber" : "2",
        "puzzlepiece" : "11",
        "puzzlepieceid" : "20"
    },
    {
        "puzzlenumber" : "2",
        "puzzlepiece" : "7",
        "puzzlepieceid" : "21"
    },
    {
        "puzzlenumber" : "2",
        "puzzlepiece" : "18",
        "puzzlepieceid" : "22"
    },
    {
        "puzzlenumber" : "2",
        "puzzlepiece" : "5",
        "puzzlepieceid" : "23"
    },
    {
        "puzzlenumber" : "2",
        "puzzlepiece" : "5",
        "puzzlepieceid" : "24"
    },
    {
        "puzzlenumber" : "2",
        "puzzlepiece" : "14",
        "puzzlepieceid" : "25"
    },
    {
        "puzzlenumber" : "2",
        "puzzlepiece" : "23",
        "puzzlepieceid" : "26"
    },
    {
        "puzzlenumber" : "2",
        "puzzlepiece" : "1",
        "puzzlepieceid" : "27"
    },
    {
        "puzzlenumber" : "2",
        "puzzlepiece" : "25",
        "puzzlepieceid" : "28"
    },
    {
        "puzzlenumber" : "2",
        "puzzlepiece" : "7",
        "puzzlepieceid" : "29"
    },
    {
        "puzzlenumber" : "2",
        "puzzlepiece" : "15",
        "puzzlepieceid" : "30"
    },
    {
        "puzzlenumber" : "2",
        "puzzlepiece" : "1",
        "puzzlepieceid" : "31"
    },
    {
        "puzzlenumber" : "2",
        "puzzlepiece" : "23",
        "puzzlepieceid" : "32"
    },
    {
        "puzzlenumber" : "2",
        "puzzlepiece" : "1",
        "puzzlepieceid" : "33"
    },
    {
        "puzzlenumber" : "2",
        "puzzlepiece" : "25",
        "puzzlepieceid" : "34"
    },
    {
        "puzzlenumber" : "2",
        "puzzlepiece" : "6",
        "puzzlepieceid" : "35"
    },
    {
        "puzzlenumber" : "2",
        "puzzlepiece" : "18",
        "puzzlepieceid" : "36"
    },
    {
        "puzzlenumber" : "2",
        "puzzlepiece" : "15",
        "puzzlepieceid" : "37"
    },
    {
        "puzzlenumber" : "2",
        "puzzlepiece" : "13",
        "puzzlepieceid" : "38"
    },
    {
        "puzzlenumber" : "2",
        "puzzlepiece" : "20",
        "puzzlepieceid" : "39"
    },
    {
        "puzzlenumber" : "2",
        "puzzlepiece" : "8",
        "puzzlepieceid" : "40"
    },
    {
        "puzzlenumber" : "2",
        "puzzlepiece" : "5",
        "puzzlepieceid" : "41"
    },
    {
        "puzzlenumber" : "2",
        "puzzlepiece" : "1",
        "puzzlepieceid" : "42"
    },
    {
        "puzzlenumber" : "2",
        "puzzlepiece" : "16",
        "puzzlepieceid" : "43"
    },
    {
        "puzzlenumber" : "2",
        "puzzlepiece" : "16",
        "puzzlepieceid" : "44"
    },
    {
        "puzzlenumber" : "2",
        "puzzlepiece" : "12",
        "puzzlepieceid" : "45"
    },
    {
        "puzzlenumber" : "2",
        "puzzlepiece" : "5",
        "puzzlepieceid" : "46"
    },
    {
        "puzzlenumber" : "2",
        "puzzlepiece" : "5",
        "puzzlepieceid" : "47"
    },
    {
        "puzzlenumber" : "2",
        "puzzlepiece" : "24",
        "puzzlepieceid" : "48"
    },
    {
        "puzzlenumber" : "2",
        "puzzlepiece" : "16",
        "puzzlepieceid" : "49"
    },
    {
        "puzzlenumber" : "2",
        "puzzlepiece" : "12",
        "puzzlepieceid" : "50"
    },
    {
        "puzzlenumber" : "2",
        "puzzlepiece" : "1",
        "puzzlepieceid" : "51"
    },
    {
        "puzzlenumber" : "2",
        "puzzlepiece" : "9",
        "puzzlepieceid" : "52"
    },
    {
        "puzzlenumber" : "2",
        "puzzlepiece" : "14",
        "puzzlepieceid" : "53"
    },
    {
        "puzzlenumber" : "2",
        "puzzlepiece" : "5",
        "puzzlepieceid" : "54"
    },
    {
        "puzzlenumber" : "2",
        "puzzlepiece" : "4",
        "puzzlepieceid" : "55"
    },
    {
        "puzzlenumber" : "2",
        "puzzlepiece" : "19",
        "puzzlepieceid" : "56"
    },
    {
        "puzzlenumber" : "2",
        "puzzlepiece" : "5",
        "puzzlepieceid" : "57"
    },
    {
        "puzzlenumber" : "2",
        "puzzlepiece" : "18",
        "puzzlepieceid" : "58"
    },
    {
        "puzzlenumber" : "2",
        "puzzlepiece" : "22",
        "puzzlepieceid" : "59"
    },
    {
        "puzzlenumber" : "2",
        "puzzlepiece" : "5",
        "puzzlepieceid" : "60"
    },
    {
        "puzzlenumber" : "2",
        "puzzlepiece" : "18",
        "puzzlepieceid" : "61"
    }
]